MANIFEST.in
README.md
package_readme.rst
requirements.txt
setup.py
test-requirements.txt
conf/conf.yaml
stacktask/__init__.py
stacktask/middleware.py
stacktask/settings.py
stacktask/test_settings.py
stacktask/urls.py
stacktask/utils.py
stacktask/wsgi.py
stacktask.egg-info/PKG-INFO
stacktask.egg-info/SOURCES.txt
stacktask.egg-info/dependency_links.txt
stacktask.egg-info/entry_points.txt
stacktask.egg-info/requires.txt
stacktask.egg-info/top_level.txt
stacktask/actions/__init__.py
stacktask/actions/models.py
stacktask/actions/openstack_clients.py
stacktask/actions/serializers.py
stacktask/actions/tests.py
stacktask/actions/user_store.py
stacktask/actions/migrations/0001_initial.py
stacktask/actions/migrations/__init__.py
stacktask/actions/openerp/__init__.py
stacktask/actions/openerp/models.py
stacktask/actions/openerp/tests.py
stacktask/actions/openerp/migrations/__init__.py
stacktask/actions/tenant_setup/__init__.py
stacktask/actions/tenant_setup/models.py
stacktask/actions/tenant_setup/serializers.py
stacktask/actions/tenant_setup/tests.py
stacktask/actions/tenant_setup/migrations/__init__.py
stacktask/api/__init__.py
stacktask/api/models.py
stacktask/api/tests.py
stacktask/api/urls.py
stacktask/api/utils.py
stacktask/api/migrations/0001_initial.py
stacktask/api/migrations/__init__.py
stacktask/api/v1/__init__.py
stacktask/api/v1/models.py
stacktask/api/v1/openstack.py
stacktask/api/v1/tasks.py
stacktask/api/v1/test_v1.py
stacktask/api/v1/urls.py
stacktask/api/v1/utils.py
stacktask/api/v1/views.py
stacktask/api/v1/templates/completed.txt
stacktask/api/v1/templates/initial.txt
stacktask/api/v1/templates/initial_password_completed.txt
stacktask/api/v1/templates/initial_password_token.txt
stacktask/api/v1/templates/invite_user_completed.txt
stacktask/api/v1/templates/invite_user_token.txt
stacktask/api/v1/templates/password_reset_completed.txt
stacktask/api/v1/templates/password_reset_token.txt
stacktask/api/v1/templates/token.txt
stacktask/api/v1/tests/__init__.py
stacktask/api/v1/tests/test_api_admin.py
stacktask/api/v1/tests/test_api_openstack.py
stacktask/api/v1/tests/test_api_taskview.py
stacktask/notifications/__init__.py
stacktask/notifications/models.py
