Metadata-Version: 1.1
Name: stacktask
Version: 0.1.3
Summary: An admin task workflow service for openstack.
Home-page: https://github.com/catalyst/stacktask
Author: Adrian Turjak
Author-email: adriant@catalyst.net.nz
License: Apache 2.0
Keywords: openstack keystone users tasks registration workflow
Platform: UNKNOWN
Classifier: Development Status :: 5 - Production/Stable
Classifier: Intended Audience :: Developers
Classifier: Intended Audience :: System Administrators
Classifier: License :: OSI Approved :: Apache Software License
Classifier: Framework :: Django :: 1.8
Classifier: Programming Language :: Python :: 2.7
Classifier: Environment :: OpenStack
